{
  "updatedAt": "2026-01-16T21:32:56.446756Z",
  "boards": {
    "overall": {
      "title": "Overall",
      "entries": [
        {
          "name": "Kiyomi",
          "occ": 97155,
          "gather": 0,
          "pvp": 1135780,
          "life": 0
        },
        {
          "name": "TasteTheeRambo",
          "occ": 96780,
          "gather": 0,
          "pvp": 923860,
          "life": 0
        },
        {
          "name": "Wawaa",
          "occ": 97355,
          "gather": 0,
          "pvp": 673910,
          "life": 0
        },
        {
          "name": "Isle lele",
          "occ": 77724,
          "gather": 0,
          "pvp": 455584,
          "life": 0
        },
        {
          "name": "Upnice)\\ i238",
          "occ": 78024,
          "gather": 0,
          "pvp": 388180,
          "life": 0
        },
        {
          "name": "Kade",
          "occ": 77424,
          "gather": 0,
          "pvp": 372068,
          "life": 0
        },
        {
          "name": "SQGEKING",
          "occ": 77424,
          "gather": 0,
          "pvp": 196816,
          "life": 0
        },
        {
          "name": "3akycka",
          "occ": 77724,
          "gather": 0,
          "pvp": 191924,
          "life": 0
        },
        {
          "name": "AlanA",
          "occ": 77424,
          "gather": 0,
          "pvp": 165476,
          "life": 0
        },
        {
          "name": "Tiho",
          "occ": 77424,
          "gather": 876,
          "pvp": 150644,
          "life": 0
        },
        {
          "name": "LUIZKER",
          "occ": 77424,
          "gather": 0,
          "pvp": 139932,
          "life": 0
        },
        {
          "name": "Rock Poli",
          "occ": 77884,
          "gather": 0,
          "pvp": 135148,
          "life": 0
        },
        {
          "name": "¢ xBrockyBx",
          "occ": 77724,
          "gather": 0,
          "pvp": 130584,
          "life": 0
        },
        {
          "name": "GuNzzy",
          "occ": 77724,
          "gather": 1028,
          "pvp": 126904,
          "life": 0
        },
        {
          "name": "Ardgenta",
          "occ": 77724,
          "gather": 0,
          "pvp": 99304,
          "life": 0
        },
        {
          "name": "1°Xzoreqqee",
          "occ": 77916,
          "gather": 0,
          "pvp": 91592,
          "life": 0
        },
        {
          "name": "Ruler",
          "occ": 77724,
          "gather": 0,
          "pvp": 70568,
          "life": 0
        },
        {
          "name": "x Inquisitor x",
          "occ": 70632,
          "gather": 2592,
          "pvp": 64584,
          "life": 0
        },
        {
          "name": "HRDFATTR",
          "occ": 77424,
          "gather": 0,
          "pvp": 29824,
          "life": 0
        },
        {
          "name": "Empire DarkMen",
          "occ": 23808,
          "gather": 0,
          "pvp": 59936,
          "life": 0
        }
      ]
    },
    "thisWeek": {
      "title": "This Week",
      "entries": []
    },
    "week_2026-01-16": {
      "title": "Week of 2026-01-16 → 2026-01-22",
      "entries": [],
      "weekOf": "2026-01-16"
    }
  }
}